[
    {
        "id": 1,
        "title": "Mr",
        "email": "testuser@gmail.com",
        "password": "test",
        "firstName": "Test",
        "lastName": "User",
        "gender": "male",
        "phone": "+918500948935"
    },
    {
        "id": 2,
        "title": "Ms",
        "email": "testuser1@gmail.com",
        "password": "test1",
        "firstName": "Test",
        "lastName": "User1",
        "gender": "female",
        "phone": "+917401473180"
    },
    {
        "id": 3,
        "title": "Mr",
        "email": "testuser2@gmail.com",
        "password": "test2",
        "firstName": "Test",
        "lastName": "User2",
        "gender": "male",
        "phone": "+919940234290"
    },
    {
        "id": 4,
        "title": "Ms",
        "email": "testuser3@gmail.com",
        "password": "test3",
        "firstName": "Test",
        "lastName": "User3",
        "gender": "female",
        "phone": "+919000000000"
    },
    {
        "id": 5,
        "title": "Mr",
        "email": "testuser4@gmail.com",
        "password": "test4",
        "firstName": "Test",
        "lastName": "User4",
        "gender": "male",
        "phone": "+919000000001"
    }
]